{
  "thumbnail": "/images/2018/marzec/2018_marzec_serdecznie_zapraszamy_2018_03_serdecznie_zapraszamy_strona-dzień-kobiet.jpg",
  "title": "Serdecznie zapraszamy",
  "publishDate": "2018-03-01T00:00:00.000Z",
  "eventDate": "2018-03-01T00:00:00.000Z",
  "content": "<div class=\"entry-content\">\n\t\t\t\t\t\t\t\n\t\t\t\t\t\t\t<p><img fetchpriority=\"high\" decoding=\"async\" class=\"aligncenter size-full wp-image-5604\" src=\"/images/2018/marzec/2018_marzec_serdecznie_zapraszamy_2018_03_serdecznie_zapraszamy_strona-dzień-kobiet.jpg\" alt=\"\" width=\"800\" height=\"565\" srcset=\"/images/2018/marzec/2018_marzec_serdecznie_zapraszamy_2018_03_serdecznie_zapraszamy_strona-dzień-kobiet.jpg 800w, /images/2018/marzec/strona-dzień-kobiet-300x212.jpg 300w, /images/2018/marzec/strona-dzień-kobiet-768x542.jpg 768w\" sizes=\"(max-width: 800px) 100vw, 800px\"></p>\n<p>&nbsp;</p>\n<p>&nbsp;</p>\n<p style=\"text-align: center;\"><em>Zawartość strony oraz wszystkie fotografie są autorstwa MGOK w Zawichoście, zgodnie</em><br>\n<em> z przepisami ustawy z dnia 4 lutego 1994 r. o prawach autorskich oraz prawach pokrewnych wszelkie prawa do fotografii i materiałów na stronie są własnością autora. Kopiowanie, powielanie i rozpowszechnianie tekstów, zdjęć, jest zabronione i wymaga zgody na piśmie.</em></p>\n\t\t\t\t\t\t\n\t\t\t\t\t\t</div>"
}