{
  "title": "Spektakl teatralny - Dziady, część 2",
  "eventDate": "2024-11-29T17:00",
  "publishDate": "2024-11-07",
  "thumbnail": "/images/2024/listopad/spektakl-teatralny---dziady-cz-2-1730989403805-0.jpeg",
  "content": [
    {
      "type": "paragraph",
      "text": "Miejsko-Gminny Ośrodek Kultury w Zawichoście serdecznie zaprasza na premierę spektaklu \"Dziady, część II\" na podstawie dramatu Adama Mickiewicza pod Patronatem Honorowym Katarzyny Kondziołki Burmistrz Zawichostu."
    },
    {
      "type": "paragraph",
      "text": "Spektakl w wykonaniu aktorów Zawichojskiego Teatru Miejskiego."
    },
    {
      "type": "paragraph",
      "text": "Scenariusz, reżyseria i scenografia - Małgorzata Fronczek."
    },
    {
      "type": "paragraph",
      "text": "Strażnica OSP w Zawichoście 29 listopada 2024 r.godz. 19.00 Cena biletu - 20 zł."
    },
    {
      "type": "paragraph",
      "text": "Bilety płatne przelewem na rachunek bankowy MGOK nr 09 9429 0004 2001 0100 1094 0001."
    },
    {
      "type": "paragraph",
      "text": "Po wpłacie bilety do odbioru w biurze MGOK."
    },
    {
      "type": "image",
      "src": "/images/2024/listopad/spektakl-teatralny---dziady-cz-2-1730989403805-0.jpeg",
      "alt": "Inline image"
    }
  ]
}